moscot/__init__.py
moscot/_constants.py
moscot/_logging.py
moscot/_registry.py
moscot/_types.py
moscot/datasets.py
moscot/py.typed
moscot/backends/__init__.py
moscot/backends/utils.py
moscot/backends/ott/__init__.py
moscot/backends/ott/_utils.py
moscot/backends/ott/output.py
moscot/backends/ott/solver.py
moscot/base/__init__.py
moscot/base/cost.py
moscot/base/output.py
moscot/base/solver.py
moscot/base/problems/__init__.py
moscot/base/problems/_mixins.py
moscot/base/problems/_utils.py
moscot/base/problems/birth_death.py
moscot/base/problems/compound_problem.py
moscot/base/problems/manager.py
moscot/base/problems/problem.py
moscot/costs/__init__.py
moscot/costs/_costs.py
moscot/costs/_utils.py
moscot/plotting/__init__.py
moscot/plotting/_plotting.py
moscot/plotting/_utils.py
moscot/problems/__init__.py
moscot/problems/_utils.py
moscot/problems/cross_modality/__init__.py
moscot/problems/cross_modality/_mixins.py
moscot/problems/cross_modality/_translation.py
moscot/problems/generic/__init__.py
moscot/problems/generic/_generic.py
moscot/problems/generic/_mixins.py
moscot/problems/space/__init__.py
moscot/problems/space/_alignment.py
moscot/problems/space/_mapping.py
moscot/problems/space/_mixins.py
moscot/problems/spatiotemporal/__init__.py
moscot/problems/spatiotemporal/_spatio_temporal.py
moscot/problems/time/__init__.py
moscot/problems/time/_lineage.py
moscot/problems/time/_mixins.py
moscot/utils/__init__.py
moscot/utils/data.py
moscot/utils/subset_policy.py
moscot/utils/tagged_array.py
moscot/utils/_data/allTFs_dmel.txt
moscot/utils/_data/allTFs_hg38.txt
moscot/utils/_data/allTFs_mm.txt
moscot/utils/_data/human_apoptosis.txt
moscot/utils/_data/human_proliferation.txt
moscot/utils/_data/mouse_apoptosis.txt
moscot/utils/_data/mouse_proliferation.txt
moscot-0.5.0.dist-info/licenses/LICENSE
moscot-0.5.0.dist-info/METADATA
moscot-0.5.0.dist-info/WHEEL
moscot-0.5.0.dist-info/top_level.txt
moscot-0.5.0.dist-info/RECORD
