Metadata-Version: 2.4
Name: moscot
Version: 0.5.0
Summary: Multi-omic single-cell optimal transport tools
Author: Dominik Klein, Giovanni Palla, Michal Klein, Zoe Piran, Marius Lange
Maintainer-email: Dominik Klein <dominik.klein@helmholtz-muenchen.de>, Giovanni Palla <giovanni.palla@helmholtz-muenchen.de>, Michal Klein <michal.klein@helmholtz-muenchen.de>
License: BSD 3-Clause License
Project-URL: Homepage, https://github.com/theislab/moscot
Project-URL: Download, https://moscot.readthedocs.io/en/latest/installation.html
Project-URL: Bug Tracker, https://github.com/theislab/moscot/issues
Project-URL: Documentation, https://moscot.readthedocs.io
Project-URL: Source Code, https://github.com/theislab/moscot
Keywords: single-cell,bio-informatics,optimal transport
Classifier: Development Status :: 4 - Beta
Classifier: Intended Audience :: Developers
Classifier: Intended Audience :: Science/Research
Classifier: Natural Language :: English
Classifier: Operating System :: POSIX :: Linux
Classifier: Operating System :: MacOS :: MacOS X
Classifier: Operating System :: Microsoft :: Windows
Classifier: Typing :: Typed
Classifier: Programming Language :: Python :: 3
Classifier: Programming Language :: Python :: 3.9
Classifier: Programming Language :: Python :: 3.10
Classifier: Topic :: Scientific/Engineering :: Bio-Informatics
Classifier: Topic :: Scientific/Engineering :: Mathematics
Requires-Python: >=3.10
License-File: LICENSE
Requires-Dist: numpy>=1.20.0
Requires-Dist: scipy>=1.7.0
Requires-Dist: pandas>=2.0.1
Requires-Dist: networkx>=3.2
Requires-Dist: matplotlib>=3.5.0
Requires-Dist: anndata>=0.9.1
Requires-Dist: scanpy>=1.9.3
Requires-Dist: wrapt>=1.13.2
Requires-Dist: docrep>=0.3.2
Requires-Dist: jax>=0.6.1
Requires-Dist: ott-jax>=0.6.0
Requires-Dist: cloudpickle>=2.2.0
Requires-Dist: rich>=13.5
Requires-Dist: docstring_inheritance>=2.0.0
Requires-Dist: mudata>=0.2.2
Requires-Dist: optax
Requires-Dist: flax
Requires-Dist: diffrax
Requires-Dist: ott-jax[neural]>=0.5.0
Provides-Extra: spatial
Requires-Dist: squidpy>=1.2.3; extra == "spatial"
Provides-Extra: dev
Requires-Dist: pre-commit>=3.0.0; extra == "dev"
Requires-Dist: tox>=4; extra == "dev"
Provides-Extra: test
Requires-Dist: pytest>=7; extra == "test"
Requires-Dist: pytest-xdist>=3; extra == "test"
Requires-Dist: pytest-mock>=3.5.0; extra == "test"
Requires-Dist: pytest-cov>=4; extra == "test"
Requires-Dist: coverage[toml]>=7; extra == "test"
Requires-Dist: moscot[neural]; extra == "test"
Provides-Extra: docs
Requires-Dist: sphinx>=5.1.1; extra == "docs"
Requires-Dist: sphinx_copybutton>=0.5.0; extra == "docs"
Requires-Dist: sphinxcontrib-bibtex>=2.3.0; extra == "docs"
Requires-Dist: sphinxcontrib-spelling>=7.6.2; extra == "docs"
Requires-Dist: sphinx-autodoc-typehints; extra == "docs"
Requires-Dist: furo>=2022.09.29; extra == "docs"
Requires-Dist: sphinx-tippy>=0.4.1; extra == "docs"
Requires-Dist: myst-nb>=0.17.1; extra == "docs"
Requires-Dist: ipython>=7.20.0; extra == "docs"
Requires-Dist: sphinx_design>=0.3.0; extra == "docs"
Dynamic: license-file
